<annotation>
	<folder></folder>
	<filename>BAG_1027_png.rf.b2cbc28edc141614a092814b7481963b.jpg</filename>
	<path>BAG_1027_png.rf.b2cbc28edc141614a092814b7481963b.jpg</path>
	<source>
		<database>roboflow.com</database>
	</source>
	<size>
		<width>640</width>
		<height>640</height>
		<depth>3</depth>
	</size>
	<segmented>0</segmented>
	<object>
		<name>SHURIKEN</name>
		<pose>Unspecified</pose>
		<truncated>0</truncated>
		<difficult>0</difficult>
		<occluded>0</occluded>
		<bndbox>
			<xmin>197</xmin>
			<xmax>338</xmax>
			<ymin>130</ymin>
			<ymax>334</ymax>
		</bndbox>
	</object>
	<object>
		<name>SHURIKEN</name>
		<pose>Unspecified</pose>
		<truncated>0</truncated>
		<difficult>0</difficult>
		<occluded>0</occluded>
		<bndbox>
			<xmin>363</xmin>
			<xmax>537</xmax>
			<ymin>100</ymin>
			<ymax>272</ymax>
		</bndbox>
	</object>
	<object>
		<name>BLADE</name>
		<pose>Unspecified</pose>
		<truncated>0</truncated>
		<difficult>0</difficult>
		<occluded>0</occluded>
		<bndbox>
			<xmin>296</xmin>
			<xmax>383</xmax>
			<ymin>353</ymin>
			<ymax>426</ymax>
		</bndbox>
	</object>
	<object>
		<name>BLADE</name>
		<pose>Unspecified</pose>
		<truncated>0</truncated>
		<difficult>0</difficult>
		<occluded>0</occluded>
		<bndbox>
			<xmin>461</xmin>
			<xmax>543</xmax>
			<ymin>449</ymin>
			<ymax>524</ymax>
		</bndbox>
	</object>
</annotation>
