<annotation>
	<folder></folder>
	<filename>BAG_0402_png.rf.ad9f16244bb7f1218e2e67f31d257f76.jpg</filename>
	<path>BAG_0402_png.rf.ad9f16244bb7f1218e2e67f31d257f76.jpg</path>
	<source>
		<database>roboflow.com</database>
	</source>
	<size>
		<width>640</width>
		<height>640</height>
		<depth>3</depth>
	</size>
	<segmented>0</segmented>
	<object>
		<name>GUN</name>
		<pose>Unspecified</pose>
		<truncated>0</truncated>
		<difficult>0</difficult>
		<occluded>0</occluded>
		<bndbox>
			<xmin>269</xmin>
			<xmax>386</xmax>
			<ymin>311</ymin>
			<ymax>344</ymax>
		</bndbox>
	</object>
	<object>
		<name>BLADE</name>
		<pose>Unspecified</pose>
		<truncated>0</truncated>
		<difficult>0</difficult>
		<occluded>0</occluded>
		<bndbox>
			<xmin>431</xmin>
			<xmax>452</xmax>
			<ymin>277</ymin>
			<ymax>336</ymax>
		</bndbox>
	</object>
</annotation>
